setup.py
npyscreenreactor/__init__.py
npyscreenreactor.egg-info/PKG-INFO
npyscreenreactor.egg-info/SOURCES.txt
npyscreenreactor.egg-info/dependency_links.txt
npyscreenreactor.egg-info/requires.txt
npyscreenreactor.egg-info/top_level.txt