Metadata-Version: 1.1
Name: npyscreenreactor
Version: 1.3
Summary: Twisted reactor for npyscreen
Home-page: https://github.com/mtearle/npyscreenreactor
Author: Mark Tearle
Author-email: mark@tearle.com
License: MIT
Download-URL: https://github.com/mtearle/npyscreenreactor/tarball/v1.3
Keywords: npyscreen,twisted
Platform: UNKNOWN
Classifier: Development Status :: 5 - Production/Stable
Classifier: Framework :: Twisted
Classifier: Intended Audience :: Developers
Classifier: License :: OSI Approved :: MIT License
Classifier: Operating System :: OS Independent
Classifier: Programming Language :: Python
Classifier: Programming Language :: Python :: 2.7
Classifier: Programming Language :: Python :: 3
Classifier: Natural Language :: English
Classifier: Topic :: Software Development :: Libraries :: Python Modules
